{"exp":1341835460,"@meta":{"serverTimeMs":20,"requestId":"019BAE70KP3RGY6VWF26"},"data":{"quotes":[{"lines":[{"stage":"repeated line when Sheldon is at the door"},{"stage":"Knock-knock-knock","quote":"Penny. ","chars":[{"nconst":"nm1433588","char":"Sheldon"}]},{"stage":"Knock-knock-knock"},{"quote":"Penny. ","chars":[{"nconst":"nm1433588","char":"Sheldon"}]},{"stage":"Knock-knock-knock"},{"quote":"Penny.","chars":[{"nconst":"nm1433588","char":"Sheldon"}]}],"qconst":"qt1101922"},{"lines":[{"stage":"repeated line"},{"quote":"Bazinga!","chars":[{"nconst":"nm1433588","char":"Sheldon"}]}],"qconst":"qt1547031"}],"tconst":"tt0898266","type":"tv_series","title":"The Big Bang Theory","year":"2007"},"copyright":"For use only by clients authorized in writing by IMDb.  Authors and users of unauthorized clients accept full legal exposure/liability for their actions."}